README.rst
setup.cfg
setup.py
src/coti_wallet/__init__.py
src/coti_wallet/base.py
src/coti_wallet/crypto_helper.py
src/coti_wallet/node_actions.py
src/coti_wallet.egg-info/PKG-INFO
src/coti_wallet.egg-info/SOURCES.txt
src/coti_wallet.egg-info/dependency_links.txt
src/coti_wallet.egg-info/requires.txt
src/coti_wallet.egg-info/top_level.txt