Metadata-Version: 2.1
Name: coti-wallet
Version: 0.0.1b11
Summary: coti wallet sdk for python
Home-page: https://github.com/coti-io/coti-sdk-python
Author: coti team
Author-email: support@coti.io
License: MIT
Keywords: coti wallet sdk
